binance_history_downloader/__init__.py
binance_history_downloader/main.py
binance_history_downloader-0.1.4.dist-info/METADATA
binance_history_downloader-0.1.4.dist-info/WHEEL
binance_history_downloader-0.1.4.dist-info/RECORD
