Metadata-Version: 2.1
Name: binance_history_downloader
Version: 0.1.4
Summary: 
License: MIT
Author: Sid
Author-email: sidnvy@gmail.com
Requires-Python: >=3.9
Classifier: License :: OSI Approved :: MIT License
Classifier: Programming Language :: Python :: 3
Classifier: Programming Language :: Python :: 3.9
Classifier: Programming Language :: Python :: 3.10
Classifier: Programming Language :: Python :: 3.11
Classifier: Programming Language :: Python :: 3.12
Requires-Dist: pandas (>=1.5.3)
Requires-Dist: tqdm (>=4.66.1,<5.0.0)
